{
  "openapi": "3.0.1",
  "info": {
    "title": "FilmesAPI",
    "version": "1.0"
  },
  "paths": {
    "/Movie": {
      "post": {
        "tags": [
          "Movie"
        ],
        "requestBody": {
          "content": {
            "application/json": {
              "schema": {
                "$ref": "#/components/schemas/Movie"
              }
            },
            "text/json": {
              "schema": {
                "$ref": "#/components/schemas/Movie"
              }
            },
            "application/*+json": {
              "schema": {
                "$ref": "#/components/schemas/Movie"
              }
            }
          }
        },
        "responses": {
          "200": {
            "description": "OK"
          }
        }
      }
    }
  },
  "components": {
    "schemas": {
      "Movie": {
        "type": "object",
        "properties": {
          "title": {
            "type": "string",
            "nullable": true
          },
          "genre": {
            "type": "string",
            "nullable": true
          },
          "duration": {
            "type": "integer",
            "format": "int32"
          }
        },
        "additionalProperties": false
      }
    }
  }
}